[
  {
    "id": 1,
    "name":"Screwdriver",
    "image":"screw_driver_small.png",
    "description":"",
    "ingredients":[
      {
        "id": 1,
        "amount": 40
      },
      {
        "id": 2,
        "amount": 100
      }
    ]
  },
  {
    "id": 2,
    "name":"Cuba Libre",
    "image":"cuba_libre_small.png",
    "description":"",
    "ingredients":[
      {
        "id": 3,
        "amount": 40
      },
      {
        "id": 4,
        "amount": 120
      }
    ]
  },
  {
    "id": 3,
    "name":"Sex on the Beach",
    "image":"sex_on_the_beach_small.png",
    "description":"",
    "ingredients":[
      {
        "id": 1,
        "amount": 40
      },
      {
        "id": 5,
        "amount": 20
      },
      {
        "id": 2,
        "amount": 40
      },
      {
        "id": 6,
        "amount": 40
      }
    ]
  },
  {
    "id": 4,
    "name":"Whiskey Cola",
    "image":"whiskey_cola_small.png",
    "description":"",
    "ingredients":[
      {
        "id": 7,
        "name": "Whiskey",
        "amount": 40
      },
      {
        "id": 4,
        "amount": 120
      }
    ]
  },
  {
    "id": 5,
    "name":"Cape Codder",
    "image":"cape_codder_small.png",
    "description":"",
    "ingredients":[
      {
        "id": 1,
        "amount": 40
      },
      {
        "id": 6,
        "amount": 120
      }
    ]
  },
  {
    "id": 6,
    "name":"Woo Woo",
    "image":"woo_woo_small.png",
    "description":"",
    "ingredients":[
      {
        "id": 1,
        "amount": 40
      },
      {
        "id": 5,
        "amount": 20
      },
      {
        "id": 6,
        "amount": 80
      }
    ]
  },
  {
    "id": 7,
    "name":"Wild Wild West",
    "image":"wild_wild_west_small.png",
    "description":"",
    "ingredients":[
      {
        "id": 7,
        "name": "Whiskey",
        "amount": 40
      },
      {
        "id": 5,
        "amount": 20
      },
      {
        "id": 6,
        "amount": 100
      }
    ]
  },
  {
    "id": 8,
    "name":"Vodka Coke",
    "image":"vodka_coke_small.png",
    "description":"",
    "ingredients":[
      {
        "id": 1,
        "amount": 40
      },
      {
        "id": 4,
        "amount": 120
      }
    ]
  },
  {
    "id": 9,
    "name":"Cuban Screw",
    "image":"cuban_screw_small.png",
    "description":"",
    "ingredients":[
      {
        "id": 3,
        "amount": 40
      },
      {
        "id": 2,
        "amount": 120
      }
    ]
  },
  {
    "id": 10,
    "name":"Sea Breeze",
    "image":"sea_breeze_small.png",
    "description":"",
    "ingredients":[
      {
        "id": 1,
        "amount": 40
      },
      {
        "id": 6,
        "amount": 100
      },
      {
        "id": 8,
        "amount": 20
      }
    ]
  },
  {
    "id": 11,
    "name":"Greyhound",
    "image":"greyhound_small.png",
    "description":"",
    "ingredients":[
      {
        "id": 1,
        "amount": 40
      },
      {
        "id": 8,
        "amount": 120
      }
    ]
  },
  {
    "id": 12,
    "name":"Jolly Rancher",
    "image":"jolly_rancher_small.png",
    "description":"",
    "ingredients":[
      {
        "id": 1,
        "amount": 40
      },
      {
        "id": 9,
        "amount": 20
      },
      {
        "id": 6,
        "amount": 100
      }
    ]
  },
  {
    "id": 13,
    "name":"Melon Ball",
    "image":"melon_ball_small.png",
    "description":"",
    "ingredients":[
      {
        "id": 1,
        "amount": 40
      },
      {
        "id": 9,
        "amount": 20
      },
      {
        "id": 2,
        "amount": 100
      }
    ]
  },
  {
    "id": 14,
    "name":"Fuzzy Navel",
    "image":"fuzzy_navel_small.png",
    "description":"",
    "ingredients":[
      {
        "id": 5,
        "amount": 40
      },
      {
        "id": 2,
        "amount": 100
      }
    ]
  },
  {
    "id": 15,
    "name":"Hairy Navel",
    "image":"fuzzy_navel_small.png",
    "description":"",
    "ingredients":[
      {
        "id": 5,
        "amount": 40
      },
      {
        "id": 1,
        "amount": 20
      },
      {
        "id": 2,
        "amount": 100
      }
    ]
  }
]
